simple_service/__init__.py
simple_service/simple_service.py
ste_test_st-0.1.17.dist-info/METADATA
ste_test_st-0.1.17.dist-info/WHEEL
ste_test_st-0.1.17.dist-info/top_level.txt
ste_test_st-0.1.17.dist-info/RECORD
