Metadata-Version: 2.1
Name: ste-test-st
Version: 0.1.17
Summary: Code example
Requires-Dist: certifi ==2023.7.22
Requires-Dist: charset-normalizer ==3.3.2
Requires-Dist: idna ==3.4
Requires-Dist: pip ==23.3.1
Requires-Dist: requests ==2.31.0
Requires-Dist: setuptools ==68.2.2
Requires-Dist: urllib3 ==2.0.7
Requires-Dist: wheel ==0.41.3
